evdev_prepared/__init__.py
evdev_prepared/device_control.py
evdev_prepared/input_dev.py
evdev_prepared/tests.py
evdev_prepared/uinput.py
evdev_prepared-0.2.3.dist-info/COPYING
evdev_prepared-0.2.3.dist-info/METADATA
evdev_prepared-0.2.3.dist-info/WHEEL
evdev_prepared-0.2.3.dist-info/top_level.txt
evdev_prepared-0.2.3.dist-info/RECORD
