Metadata-Version: 2.1
Name: evdev-prepared
Version: 0.2.3
Summary: Useful classes to make usage of python evdev easier
Home-page: https://github.com/dp0s/evdev_prepared
Author: DPS
Author-email: dps@my.mail.de
License: UNKNOWN
Platform: UNKNOWN
Classifier: Programming Language :: Python :: 3
Classifier: License :: OSI Approved :: GNU General Public License v3 (GPLv3)
Requires-Python: >=3.6
Requires-Dist: setuptools (>=45)
Requires-Dist: evdev (>=1.4.0)
